mac/mac.v
module mac (instruction, multiplier, multiplicand, stall, clk, reset_n, result, protect);
input signed [15:0] multiplier;
input signed [15:0] multiplicand; 
input  clk;
input  reset_n;
input  stall;
input  [2:0] instruction;
output reg [31:0] result;
output reg [7:0] protect;

reg [2:0] curIns;
reg [2:0] preIns;

reg [39:0] pipe1 = 40'b0;
reg [39:0] pipe2 = 40'b0;

reg [39:0] zero = 40'b0;

  always@(posedge clk or negedge reset_n) begin
    if(~reset_n) begin
      result <= 32'b0;
      protect <= 8'b0;
    end else if (~stall) begin
      curIns <= instruction;
      if (instruction[2] == 0)
        pipe1 <= multiplier * multiplicand;
      else begin
        {pipe1[35:32],pipe1[15:0]} <= $signed(multiplier[7:0]) * $signed(multiplicand[7:0]);
        {pipe1[39:36],pipe1[31:16]} <= $signed(multiplier[15:8]) * $signed(multiplicand[15:8]);
      end
    end else begin
      curIns <= curIns;
      pipe1 <= pipe1;
    end
  end

  always@(posedge clk) begin
    preIns = curIns;
    if (~stall)
      {protect, result} <= pipe2;
    else begin
      {protect, result} <= {protect, result};
      pipe2 <= pipe2;
    end
    case(preIns)
      3'b000: begin
        pipe2 = zero;
      end
      3'b001: begin
        pipe2 = pipe1;
      end
      3'b010: begin
        pipe2 = pipe2 + pipe1;
      end
      3'b011: begin
        if ($signed(pipe2) > $signed(40'h007FFFFFFF))
          pipe2 = {protect,32'h7FFFFFFF};
        else if ($signed(pipe2) < $signed(40'hFF80000000))
          pipe2 = {protect,32'h80000000};
        else
          pipe2 = pipe2;
      end
      3'b100: begin
        pipe2 = zero;
      end
      3'b101: begin
        {pipe2[35:32],pipe2[15:0]} = {pipe1[35:32],pipe1[15:0]};
        {pipe2[39:36],pipe2[31:16]} = {pipe1[39:36],pipe1[31:16]};
      end
      3'b110: begin
        {pipe2[35:32],pipe2[15:0]} = $signed({pipe2[35:32],pipe2[15:0]}) + $signed({pipe1[35:32],pipe1[15:0]});
        {pipe2[39:36],pipe2[31:16]} = $signed({pipe2[39:36],pipe2[31:16]}) + $signed({pipe1[39:36],pipe1[31:16]});
      end
      3'b111: begin
        if ($signed({pipe2[35:32],pipe2[15:0]}) > $signed(20'h07FFF))
          {pipe2[35:32],pipe2[15:0]} = {protect[3:0],16'h7FFF};
        else if ($signed({pipe2[35:32],pipe2[15:0]}) < $signed(20'hF8000))
          {pipe2[35:32],pipe2[15:0]} = {protect[3:0],16'h8000};
        else
          {pipe2[35:32],pipe2[15:0]} = {pipe2[35:32],pipe2[15:0]};

        if ($signed({pipe2[39:36],pipe2[31:16]}) > $signed(20'h07FFF))
          {pipe2[39:36],pipe2[31:16]} = {protect[7:4],16'h7FFF};
        else if ($signed({pipe2[39:36],pipe2[31:16]}) < $signed(20'hF8000))
          {pipe2[39:36],pipe2[31:16]} = {protect[7:4],16'h8000};
        else
          {pipe2[39:36],pipe2[31:16]} = {pipe2[39:36],pipe2[31:16]};
      end
    endcase
  end

endmodule

mac/testfixture.v
// +FHDR------------------------------------------------------------------------
// Copyright (c) 2002, Global UniChip Corporation (UniChip).
// UniChip's Proprietary/Confidential
//
// All rights reserved. No part of this design may be reproduced or stored
// in a retrieval system, or transmitted, in any form or by any means,
// electronic, mechanical, photocopying, recording, or otherwise,
// without prior written permission of the Global UniChip Corporation.
// Unauthorized reproduction, duplication, use, or disclosure of this
// design will be deemed as infringement.
// -----------------------------------------------------------------------------
// FILE   : $Id: dic_2003.v,v 1.1 2003/04/25 04:01:19 ip01_11a Exp $
// TYPE   : Verilog Module
// AUTHOR : Tian-Sheuan Chang 
// -----------------------------------------------------------------------------
// KEYWORDS : 
// -----------------------------------------------------------------------------
// PURPOSE : 
// -----------------------------------------------------------------------------
// PARAMETERS
// PARAM_NAME RANGE : DESCRIPTION : DEFAULT
// N/A
// -----------------------------------------------------------------------------
// REUSE ISSUES
// Reset Strategy :  rst_n
// Clock Domains :   clk
// Critical Timing :
// Test Features :   N/A
// Asynchronous I/F :N/A
// Scan Methodology :MUX-based scan F.F.
// Instantiations :  N/A
// Other :           N/A
// -FHDR------------------------------------------------------------------------

`timescale 1ns/10ps
module mac_sim;
//define for simulator parameters
`define HPHASE 10
//`define FSDB 1
`define CYCLE (`HPHASE * 2)
`define DUMPFILE_NAME "mac.fsdb"
//define for instruction
parameter CLEAR =  3'b000;
parameter CLEAR2 = 3'b100;
parameter MUL_16 = 3'b001;
parameter MAC_16 = 3'b010;
parameter SAT_16 = 3'b011;
parameter MUL_8  = 3'b101;
parameter MAC_8  = 3'b110;
parameter SAT_8  = 3'b111;

parameter NO_STALL = 0;
parameter STALL    = 1;
// -----------------------------------------------------------------------------
// Constant declarations
// -----------------------------------------------------------------------------

// -----------------------------------------------------------------------------
// Signal declarations
// -----------------------------------------------------------------------------

reg             reset_n;
reg             clk;
reg             stall;
reg [2:0]       instruction;
reg [15:0]      multiplier;
reg [15:0]      multiplicand;

// Beginning of automatic wires (for instantiated-module outputs)
wire [7:0]		protect;		// From u_mac of mac.v, ...
wire [31:0]		result;			// From u_mac of mac.v, ...
reg [7:0]		protect_g;		// From u_mac of mac.v, ...
reg [31:0]		result_g;		// From u_mac of mac.v, ...


// End of automatics

// ========================= Start of Main Code ================================
  mac u_mac(/*autoinst*/
	    // Outputs
	    .result			(result[31:0]),
	    .protect			(protect[7:0]),
	    // Inputs
	    .reset_n			(reset_n),
	    .clk			(clk),
	    .multiplier			(multiplier[15:0]),
	    .multiplicand		(multiplicand[15:0]),
	    .instruction		(instruction[2:0]),
	    .stall			(stall));
  
//---- clock generation
always begin
  #(`HPHASE) clk = 1'b0;
  #(`HPHASE) clk = 1'b1;
end

reg [31:0] cycle_cnt;

always @(posedge clk or negedge reset_n)
  if(~reset_n) 
    cycle_cnt <= 0;
  else
    cycle_cnt <= cycle_cnt + 1'b1;

integer result_file1;
integer result_file2;
reg  [39:0] data_base [0:85];
initial $readmemh("EXPECT.DAT", data_base);

integer i;
reg    [39:0] data_tmp;
reg    [9:0]  error_cnt;
reg     ready;

initial begin
      error_cnt = 0;
      @(negedge clk); // start to compare from 2nd cycle
      for  (i = 1; i <= 86; i = i + 1) begin
         data_tmp = data_base[i-1];
         @(negedge clk);
         if (protect !== data_tmp[39:32]) begin
           $display ("ERROR at cycle_cnt= %d: protect(%h)!= EXPECT(%h)", 
                      cycle_cnt, protect, data_tmp[39:32]); 
           error_cnt = error_cnt + 1;
         end
         if (result !== data_tmp[31:0]) begin
           $display ("ERROR at cycle_cnt= %d: result(%h)!= EXPECT(%h)", 
                      cycle_cnt,  result, data_tmp[31:0]); 
           error_cnt = error_cnt + 1;
         end
     end

     if(error_cnt == 10'b0) begin
      $display ("=================================================");
      $display ("Congratulation!, Your design PASSed all the test patterns "); 
      $display ("=================================================");
     end
     else begin
      $display ("=================================================");
      $display ("There're %d errors in your design", error_cnt); 
      $display ("=================================================");
     end
end  

/*
initial 
  $sdf_annotate ("chip.sdf", u_mac);
*/


initial begin
/*  result_file1 = $fopen("mac_rst.txt"); */
/*    result_file2 = $fopen("EXPECT.DAT");    */
  dump_vcd;
  #0 
  clk = 1; 
  reset_n = 1; 
  stall = 1'b0;
  multiplier = 16'bz;
  multiplicand = 16'bz;
  instruction = 3'bz;
  error_cnt = 0;
  ready     = 0;
  $display("start test");
  #(`HPHASE)
     reset_n = 0;
  #(`CYCLE-0.1)  // to prevent from race condition by ccyang
     reset_n = 1;
     test_mac_16;
     test_mac_8;
  #(3* `CYCLE)
     $finish;
end

task test_mac_8;
  begin
  //********************
  mac_tsk(CLEAR, NO_STALL, 16'hff11, 16'h11ff, 0, 0);  

  $display("------------------------------");
  $display("b1. test MUL_8, cycle = %h", cycle_cnt);
  mac_tsk(MUL_8, NO_STALL, 16'h7f7f, 16'h7f7f, protect_g, result_g);  
  mac_tsk(MUL_8, NO_STALL, 16'h8080, 16'h8080, protect_g, result_g);  
  mac_tsk(MUL_8, NO_STALL, 16'h7f7f, 16'h8080, protect_g, result_g);  
  mac_tsk(MUL_8, NO_STALL, 16'h3031, 16'h232f, protect_g, result_g);  
  
  $display("------------------------------");
  $display("b2. test MAC_8, overflow, cycle = %h", cycle_cnt);
  mac_tsk(MAC_8, NO_STALL, 16'h7f7f, 16'h7f7f, protect_g, result_g);  
  mac_tsk(MAC_8, NO_STALL, 16'h7f7f, 16'h7f7f, protect_g, result_g);  
  mac_tsk(MAC_8, NO_STALL, 16'h7f7f, 16'h7f7f, protect_g, result_g);  

  mac_tsk(SAT_8, NO_STALL, 16'h8080, 16'h8080, protect_g, result_g);  

  mac_tsk(MAC_8, NO_STALL, 16'h7f7f, 16'h7f7f, protect_g, result_g);  
  mac_tsk(MAC_8, NO_STALL, 16'h7f7f, 16'h7f7f, protect_g, result_g);  
  mac_tsk(MAC_8, NO_STALL, 16'h7f7f, 16'h7f7f, protect_g, result_g);  
  mac_tsk(MAC_8, NO_STALL, 16'h7f7f, 16'h7f7f, protect_g, result_g);  
  mac_tsk(MAC_8, NO_STALL, 16'h7f7f, 16'h7f7f, protect_g, result_g);  
  mac_tsk(MAC_8, NO_STALL, 16'h7f7f, 16'h7f7f, protect_g, result_g);  
  mac_tsk(MAC_8, NO_STALL, 16'h7f7f, 16'h7f7f, protect_g, result_g);  
  mac_tsk(MAC_8, NO_STALL, 16'h7f7f, 16'h7f7f, protect_g, result_g);  

  $display("------------------------------");
  $display("b3. test stall, cycle = %h", cycle_cnt);
  mac_tsk(SAT_8,    STALL,    16'h8080, 16'h8080, protect_g, result_g);  
  mac_tsk(SAT_8,    NO_STALL, 16'h8080, 16'h8080, protect_g, result_g);  
  
  $display("------------------------------");
  $display("b4. test SAT_8, cycle = %h", cycle_cnt);
  mac_tsk(SAT_8, NO_STALL, 16'h8080, 16'h8080, protect_g, result_g);  
  mac_tsk(CLEAR, NO_STALL, 16'hff11, 16'h11ff, protect_g, result_g);  

  $display("------------------------------");
  $display("b5. test MAC_8, cycle = %h", cycle_cnt);
  mac_tsk(MAC_8, NO_STALL, 16'h807f, 16'h7f7f, protect_g, result_g);  
  mac_tsk(MAC_8, NO_STALL, 16'h807f, 16'h7f7f, protect_g, result_g);  
  mac_tsk(MAC_8, NO_STALL, 16'h807f, 16'h7f7f, protect_g, result_g);  

  mac_tsk(SAT_8, NO_STALL, 16'h807f, 16'h8080, protect_g, result_g);  

  mac_tsk(MAC_8, NO_STALL, 16'h807f, 16'h7f7f, protect_g, result_g);  
  mac_tsk(MAC_8, NO_STALL, 16'h807f, 16'h7f7f, protect_g, result_g);  
  mac_tsk(MAC_8, NO_STALL, 16'h807f, 16'h7f7f, protect_g, result_g);  
  mac_tsk(MAC_8, NO_STALL, 16'h807f, 16'h7f7f, protect_g, result_g);  
  mac_tsk(MAC_8, NO_STALL, 16'h807f, 16'h7f7f, protect_g, result_g);  
  mac_tsk(MAC_8, NO_STALL, 16'h807f, 16'h7f7f, protect_g, result_g);  
  mac_tsk(MAC_8, NO_STALL, 16'h807f, 16'h7f7f, protect_g, result_g);  
  mac_tsk(MAC_8, NO_STALL, 16'h807f, 16'h7f7f, protect_g, result_g);  

  $display("------------------------------");
  $display("b6. stall insertion, cycle = %h", cycle_cnt);
  mac_tsk(SAT_8,    STALL, 16'h8080, 16'h8080, protect_g, result_g);  
  mac_tsk(SAT_8,    STALL, 16'h8080, 16'h8080, protect_g, result_g);  
  mac_tsk(SAT_8, NO_STALL, 16'h8080, 16'h8080, protect_g, result_g);  
  mac_tsk(SAT_8, NO_STALL, 16'h8080, 16'h8080, protect_g, result_g);  
  mac_tsk(MAC_8, NO_STALL, 16'h8080, 16'h7f7f, protect_g, result_g);  
  
  $display("b7. test stall, cycle = %h", cycle_cnt);
  mac_tsk(SAT_8,      STALL, 16'h8080, 16'h8080, protect_g, result_g);  
  mac_tsk(SAT_8,   NO_STALL, 16'h8080, 16'h8080, protect_g, result_g);  

  $display("b8. test SAT_8, cycle = %h", cycle_cnt);
  mac_tsk(SAT_8, NO_STALL, 16'h8080, 16'h8080, protect_g, result_g); 
  mac_tsk(CLEAR, NO_STALL, 16'hff11, 16'h11ff, protect_g, result_g);  

  //********************
  end
endtask

task test_mac_16;
  begin
  //********************
  mac_tsk(CLEAR, NO_STALL, 16'hff11, 16'h11ff, 0, 0);  

  $display("------------------------------");
  $display("a1. test MUL_16, cycle = %h", cycle_cnt);
  mac_tsk(MUL_16, NO_STALL, 16'h7fff, 16'h7fff, protect_g, result_g);  
  mac_tsk(MUL_16, NO_STALL, 16'h8000, 16'h8000, protect_g, result_g);  
  mac_tsk(MUL_16, NO_STALL, 16'h7fff, 16'h8000, protect_g, result_g);  
  mac_tsk(MUL_16, NO_STALL, 16'h3031, 16'h232f, protect_g, result_g);  
  
  $display("------------------------------");
  $display("a2. test MAC_16, overflow, cycle = %h", cycle_cnt);
  mac_tsk(MAC_16, NO_STALL, 16'h7fff, 16'h7fff, protect_g, result_g);  
  mac_tsk(MAC_16, NO_STALL, 16'h7fff, 16'h7fff, protect_g, result_g);  
  mac_tsk(MAC_16, NO_STALL, 16'h7fff, 16'h7fff, protect_g, result_g);  

  mac_tsk(SAT_16, NO_STALL, 16'h8000, 16'h8000, protect_g, result_g);  

  mac_tsk(MAC_16, NO_STALL, 16'h7fff, 16'h7fff, protect_g, result_g);  
  mac_tsk(MAC_16, NO_STALL, 16'h7fff, 16'h7fff, protect_g, result_g);  
  mac_tsk(MAC_16, NO_STALL, 16'h7fff, 16'h7fff, protect_g, result_g);  
  mac_tsk(MAC_16, NO_STALL, 16'h7fff, 16'h7fff, protect_g, result_g);  
  mac_tsk(MAC_16, NO_STALL, 16'h7fff, 16'h7fff, protect_g, result_g);  
  mac_tsk(MAC_16, NO_STALL, 16'h7fff, 16'h7fff, protect_g, result_g);  
  mac_tsk(MAC_16, NO_STALL, 16'h7fff, 16'h7fff, protect_g, result_g);  
  mac_tsk(MAC_16, NO_STALL, 16'h7fff, 16'h7fff, protect_g, result_g);  

  $display("------------------------------");
  $display("a3. test stall, cycle = %h", cycle_cnt);
  mac_tsk(SAT_16,    STALL, 16'h8000, 16'h8000, protect_g, result_g);  
  mac_tsk(SAT_16, NO_STALL, 16'h8000, 16'h8000, protect_g, result_g);  
  
  $display("------------------------------");
  $display("a4. test SAT_16, cycle = %h", cycle_cnt);
  mac_tsk(SAT_16, NO_STALL, 16'h8000, 16'h8000, protect_g, result_g);  
  mac_tsk(CLEAR,  NO_STALL, 16'hff11, 16'h11ff, protect_g, result_g);  

  $display("------------------------------");
  $display("a5. test MAC_16, cycle = %h", cycle_cnt);
  mac_tsk(MAC_16, NO_STALL, 16'h8000, 16'h7fff, protect_g, result_g);  
  mac_tsk(MAC_16, NO_STALL, 16'h8000, 16'h7fff, protect_g, result_g);  
  mac_tsk(MAC_16, NO_STALL, 16'h8000, 16'h7fff, protect_g, result_g);  

  mac_tsk(SAT_16, NO_STALL, 16'h8000, 16'h8000, protect_g, result_g);  

  mac_tsk(MAC_16, NO_STALL, 16'h8000, 16'h7fff, protect_g, result_g);  
  mac_tsk(MAC_16, NO_STALL, 16'h8000, 16'h7fff, protect_g, result_g);  
  mac_tsk(MAC_16, NO_STALL, 16'h8000, 16'h7fff, protect_g, result_g);  
  mac_tsk(MAC_16, NO_STALL, 16'h8000, 16'h7fff, protect_g, result_g);  
  mac_tsk(MAC_16, NO_STALL, 16'h8000, 16'h7fff, protect_g, result_g);  
  mac_tsk(MAC_16, NO_STALL, 16'h8000, 16'h7fff, protect_g, result_g);  
  mac_tsk(MAC_16, NO_STALL, 16'h8000, 16'h7fff, protect_g, result_g);  
  mac_tsk(MAC_16, NO_STALL, 16'h8000, 16'h7fff, protect_g, result_g);  

  $display("------------------------------");
  $display("a6. stall insertion, cycle = %h", cycle_cnt);
  mac_tsk(SAT_16,    STALL, 16'h8000, 16'h8000, protect_g, result_g);  
  mac_tsk(SAT_16,    STALL, 16'h8000, 16'h8000, protect_g, result_g);  
  mac_tsk(SAT_16, NO_STALL, 16'h8000, 16'h8000, protect_g, result_g);  
  mac_tsk(SAT_16,    STALL, 16'h8000, 16'h8000, protect_g, result_g);  
  mac_tsk(MAC_16, NO_STALL, 16'h8000, 16'h7fff, protect_g, result_g);  
  
  $display("a7. test stall, cycle = %h", cycle_cnt);
  mac_tsk(SAT_16,    STALL, 16'h8000, 16'h8000, protect_g, result_g);  

  $display("a8. test SAT_16, cycle = %h", cycle_cnt);
  mac_tsk(SAT_16, NO_STALL, 16'h8000, 16'h8000, protect_g, result_g); 
  mac_tsk(CLEAR,  NO_STALL, 16'hff11, 16'h11ff, protect_g, result_g);  

  //********************
  
  end
endtask

task mac_tsk;
  input [2:0] instruction_t;
  input stall_t;
  input [15:0] a;
  input [15:0] b;
  
  input [7:0] protect_t; //unused, for on-line verification
  input [31:0] result_t; //unused, for on-line verification
  
  begin
    @(negedge clk)
    #(`CYCLE*0.3)
      instruction = instruction_t;
      multiplier = a;
      multiplicand = b;
      stall = stall_t; 
      protect_g = protect_t;
      result_g = result_t;
    #(`CYCLE*0.4)
      instruction = 3'bz;
      multiplier = 16'bz;
      multiplicand = 16'bz;
      stall = 1'b0;
      protect_g = protect_t;
      result_g = result_t;  
  end
endtask  

//*********************
//compare result
//*********************
always @(negedge clk) begin
//  $fdisplay(result_file1,"cycles = %h,  %h,  %h", cycle_cnt, protect, result);
//    $fdisplay(result_file2,"%h%h", protect, result);
  end

//*********************
// Dump waveform
//*********************

task dump_vcd;
begin
$dumpfile("mac.vcd");
$dumpvars;    
`ifdef FSDB
  //$fsdbVersion;
  $fsdbDumpfile(`DUMPFILE_NAME);
  $fsdbDumpvars;
`endif
 end
endtask

endmodule // module_name

// ============================ End of Module ==================================
// Revision History
// $Log: dic_2003.v,v $
// Revision 1.1  2003/04/25 04:01:19  ip01_11a
// for ic test
//
// Revision 1.1.1.1  2003/04/15 03:30:42  ip01_11a
// first version
//

mac/mac.vcd
$date
	Thu Apr 28 04:08:14 2022
$end
$version
	Icarus Verilog
$end
$timescale
	10ps
$end
$scope module mac_sim $end
$var wire 32 ! result [31:0] $end
$var wire 8 " protect [7:0] $end
$var reg 1 # clk $end
$var reg 32 $ cycle_cnt [31:0] $end
$var reg 40 % data_tmp [39:0] $end
$var reg 10 & error_cnt [9:0] $end
$var reg 3 ' instruction [2:0] $end
$var reg 16 ( multiplicand [15:0] $end
$var reg 16 ) multiplier [15:0] $end
$var reg 8 * protect_g [7:0] $end
$var reg 1 + ready $end
$var reg 1 , reset_n $end
$var reg 32 - result_g [31:0] $end
$var reg 1 . stall $end
$var integer 32 / i [31:0] $end
$scope module u_mac $end
$var wire 1 # clk $end
$var wire 3 0 instruction [2:0] $end
$var wire 16 1 multiplicand [15:0] $end
$var wire 16 2 multiplier [15:0] $end
$var wire 1 , reset_n $end
$var wire 1 . stall $end
$var reg 3 3 curIns [2:0] $end
$var reg 40 4 pipe1 [39:0] $end
$var reg 40 5 pipe2 [39:0] $end
$var reg 3 6 preIns [2:0] $end
$var reg 8 7 protect [7:0] $end
$var reg 32 8 result [31:0] $end
$var reg 40 9 zero [39:0] $end
$upscope $end
$scope task dump_vcd $end
$upscope $end
$scope task mac_tsk $end
$var reg 16 : a [15:0] $end
$var reg 16 ; b [15:0] $end
$var reg 3 < instruction_t [2:0] $end
$var reg 8 = protect_t [7:0] $end
$var reg 32 > result_t [31:0] $end
$var reg 1 ? stall_t $end
$upscope $end
$scope task test_mac_16 $end
$upscope $end
$scope task test_mac_8 $end
$upscope $end
$upscope $end
$enddefinitions $end
#0
$dumpvars
x?
bx >
bx =
bx <
bx ;
bx :
b0 9
b0 8
b0 7
bx 6
b0 5
bx 4
bz 3
bz 2
bz 1
bz 0
bx /
0.
bx -
1,
0+
bx *
bz )
bz (
bz '
b0 &
bx %
bx $
1#
b0 "
b0 !
$end
#1000
b0 $
b0 %
b1 /
0,
0#
#2000
bz 6
1#
#2990
b0 >
b0 =
b1000111111111 ;
b1111111100010001 :
0?
b0 <
1,
#3000
b10 /
0#
#3600
b0 -
b0 *
b1000111111111 (
b1000111111111 1
b1111111100010001 )
b1111111100010001 2
b0 '
b0 0
#4000
b1 $
b1111111111111111111011110011001011101111 4
b0 3
1#
#4400
b111111111111111 ;
b111111111111111 :
b1 <
bz (
bz 1
bz )
bz 2
bz '
bz 0
#5000
b11 /
0#
#5600
b111111111111111 (
b111111111111111 1
b111111111111111 )
b111111111111111 2
b1 '
b1 0
#6000
b111111111111110000000000000001 4
b1 3
b10 $
b0 6
1#
#6400
b1000000000000000 ;
b1000000000000000 :
bz (
bz 1
bz )
bz 2
bz '
bz 0
#7000
b100 /
0#
#7600
b1000000000000000 (
b1000000000000000 1
b1000000000000000 )
b1000000000000000 2
b1 '
b1 0
#8000
b11 $
b1000000000000000000000000000000 4
b111111111111110000000000000001 5
b1 6
1#
#8400
b111111111111111 :
bz (
bz 1
bz )
bz 2
bz '
bz 0
#9000
b111111111111110000000000000001 %
b101 /
0#
#9600
b1000000000000000 (
b1000000000000000 1
b111111111111111 )
b111111111111111 2
b1 '
b1 0
#10000
b111111111111110000000000000001 !
b111111111111110000000000000001 8
b1111111111000000000000001000000000000000 4
b100 $
b1000000000000000000000000000000 5
1#
#10400
b10001100101111 ;
b11000000110001 :
bz (
bz 1
bz )
bz 2
bz '
bz 0
#11000
b1000000000000000000000000000000 %
b110 /
0#
#11600
b10001100101111 (
b10001100101111 1
b11000000110001 )
b11000000110001 2
b1 '
b1 0
#12000
b1000000000000000000000000000000 !
b1000000000000000000000000000000 8
b101 $
b110100111111000101111111111 4
b1111111111000000000000001000000000000000 5
1#
#12400
b111111111111111 ;
b111111111111111 :
b10 <
bz (
bz 1
bz )
bz 2
bz '
bz 0
#13000
b1111111111000000000000001000000000000000 %
b111 /
0#
#13600
b111111111111111 (
b111111111111111 1
b111111111111111 )
b111111111111111 2
b10 '
b10 0
#14000
b11111111 "
b11111111 7
b11000000000000001000000000000000 !
b11000000000000001000000000000000 8
b111111111111110000000000000001 4
b10 3
b110 $
b110100111111000101111111111 5
1#
#14400
bz (
bz 1
bz )
bz 2
bz '
bz 0
#15000
b110100111111000101111111111 %
b1000 /
0#
#15600
b111111111111111 (
b111111111111111 1
b111111111111111 )
b111111111111111 2
b10 '
b10 0
#16000
b0 "
b0 7
b110100111111000101111111111 !
b110100111111000101111111111 8
b111 $
b1000110100111101000110000000000 5
b10 6
1#
#16400
bz (
bz 1
bz )
bz 2
bz '
bz 0
#17000
b1000110100111101000110000000000 %
b1001 /
0#
#17600
b111111111111111 (
b111111111111111 1
b111111111111111 )
b111111111111111 2
b10 '
b10 0
#18000
b1000110100111101000110000000000 !
b1000110100111101000110000000000 8
b1000 $
b10000110100111011000110000000001 5
1#
#18400
b1000000000000000 ;
b1000000000000000 :
b11 <
bz (
bz 1
bz )
bz 2
bz '
bz 0
#19000
b10000110100111011000110000000001 %
b1010 /
0#
#19600
b1000000000000000 (
b1000000000000000 1
b1000000000000000 )
b1000000000000000 2
b11 '
b11 0
#20000
b10000110100111011000110000000001 !
b10000110100111011000110000000001 8
b1001 $
b1000000000000000000000000000000 4
b11 3
b11000110100111001000110000000010 5
1#
#20400
b111111111111111 ;
b111111111111111 :
b10 <
bz (
bz 1
bz )
bz 2
bz '
bz 0
#21000
b11000110100111001000110000000010 %
b1011 /
0#
#21600
b111111111111111 (
b111111111111111 1
b111111111111111 )
b111111111111111 2
b10 '
b10 0
#22000
b11000110100111001000110000000010 !
b11000110100111001000110000000010 8
b111111111111110000000000000001 4
b10 3
b1010 $
b1111111111111111111111111111111 5
b11 6
1#
#22400
bz (
bz 1
bz )
bz 2
bz '
bz 0
#23000
b1111111111111111111111111111111 %
b1100 /
0#
#23600
b111111111111111 (
b111111111111111 1
b111111111111111 )
b111111111111111 2
b10 '
b10 0
#24000
b1111111111111111111111111111111 !
b1111111111111111111111111111111 8
b1011 $
b10111111111111110000000000000000 5
b10 6
1#
#24400
bz (
bz 1
bz )
bz 2
bz '
bz 0
#25000
b10111111111111110000000000000000 %
b1101 /
0#
#25600
b111111111111111 (
b111111111111111 1
b111111111111111 )
b111111111111111 2
b10 '
b10 0
#26000
b10111111111111110000000000000000 !
b10111111111111110000000000000000 8
b1100 $
b11111111111111100000000000000001 5
1#
#26400
bz (
bz 1
bz )
bz 2
bz '
bz 0
#27000
b11111111111111100000000000000001 %
b1110 /
0#
#27600
b111111111111111 (
b111111111111111 1
b111111111111111 )
b111111111111111 2
b10 '
b10 0
#28000
b11111111111111100000000000000001 !
b11111111111111100000000000000001 8
b1101 $
b100111111111111010000000000000010 5
1#
#28400
bz (
bz 1
bz )
bz 2
bz '
bz 0
#29000
b100111111111111010000000000000010 %
b1111 /
0#
#29600
b111111111111111 (
b111111111111111 1
b111111111111111 )
b111111111111111 2
b10 '
b10 0
#30000
b1 "
b1 7
b111111111111010000000000000010 !
b111111111111010000000000000010 8
b1110 $
b101111111111111000000000000000011 5
1#
#30400
bz (
bz 1
bz )
bz 2
bz '
bz 0
#31000
b101111111111111000000000000000011 %
b10000 /
0#
#31600
b111111111111111 (
b111111111111111 1
b111111111111111 )
b111111111111111 2
b10 '
b10 0
#32000
b1111111111111000000000000000011 !
b1111111111111000000000000000011 8
b1111 $
b110111111111110110000000000000100 5
1#
#32400
bz (
bz 1
bz )
bz 2
bz '
bz 0
#33000
b110111111111110110000000000000100 %
b10001 /
0#
#33600
b111111111111111 (
b111111111111111 1
b111111111111111 )
b111111111111111 2
b10 '
b10 0
#34000
b10111111111110110000000000000100 !
b10111111111110110000000000000100 8
b10000 $
b111111111111110100000000000000101 5
1#
#34400
bz (
bz 1
bz )
bz 2
bz '
bz 0
#35000
b111111111111110100000000000000101 %
b10010 /
0#
#35600
b111111111111111 (
b111111111111111 1
b111111111111111 )
b111111111111111 2
b10 '
b10 0
#36000
b11111111111110100000000000000101 !
b11111111111110100000000000000101 8
b10001 $
b1000111111111110010000000000000110 5
1#
#36400
b1000000000000000 ;
b1000000000000000 :
1?
b11 <
bz (
bz 1
bz )
bz 2
bz '
bz 0
#37000
b10011 /
0#
#37600
1.
b1000000000000000 (
b1000000000000000 1
b1000000000000000 )
b1000000000000000 2
b11 '
b11 0
#38000
b10010 $
b1000111111111110010000000000000110 5
1#
#38400
0?
0.
bz (
bz 1
bz )
bz 2
bz '
bz 0
#39000
b1000111111111110010000000000000110 %
b10100 /
0#
#39600
b1000000000000000 (
b1000000000000000 1
b1000000000000000 )
b1000000000000000 2
b11 '
b11 0
#40000
b10 "
b10 7
b111111111110010000000000000110 !
b111111111110010000000000000110 8
b10011 $
b1000000000000000000000000000000 4
b11 3
b1001111111111110000000000000000111 5
1#
#40400
bz (
bz 1
bz )
bz 2
bz '
bz 0
#41000
b1001111111111110000000000000000111 %
b10101 /
0#
#41600
b1000000000000000 (
b1000000000000000 1
b1000000000000000 )
b1000000000000000 2
b11 '
b11 0
#42000
b1111111111110000000000000000111 !
b1111111111110000000000000000111 8
b10100 $
b1001111111111111111111111111111111 5
b11 6
1#
#42400
b1000111111111 ;
b1111111100010001 :
b0 <
bz (
bz 1
bz )
bz 2
bz '
bz 0
#43000
b1001111111111111111111111111111111 %
b10110 /
0#
#43600
b1000111111111 (
b1000111111111 1
b1111111100010001 )
b1111111100010001 2
b0 '
b0 0
#44000
b1111111111111111111111111111111 !
b1111111111111111111111111111111 8
b10101 $
b1111111111111111111011110011001011101111 4
b0 3
1#
#44400
b111111111111111 ;
b1000000000000000 :
b10 <
bz (
bz 1
bz )
bz 2
bz '
bz 0
#45000
b10111 /
0#
#45600
b111111111111111 (
b111111111111111 1
b1000000000000000 )
b1000000000000000 2
b10 '
b10 0
#46000
b1111111111000000000000001000000000000000 4
b10 3
b10110 $
b0 5
b0 6
1#
#46400
bz (
bz 1
bz )
bz 2
bz '
bz 0
#47000
b0 %
b11000 /
0#
#47600
b111111111111111 (
b111111111111111 1
b1000000000000000 )
b1000000000000000 2
b10 '
b10 0
#48000
b0 "
b0 7
b0 !
b0 8
b10111 $
b1111111111000000000000001000000000000000 5
b10 6
1#
#48400
bz (
bz 1
bz )
bz 2
bz '
bz 0
#49000
b1111111111000000000000001000000000000000 %
b11001 /
0#
#49600
b111111111111111 (
b111111111111111 1
b1000000000000000 )
b1000000000000000 2
b10 '
b10 0
#50000
b11111111 "
b11111111 7
b11000000000000001000000000000000 !
b11000000000000001000000000000000 8
b11000 $
b1111111110000000000000010000000000000000 5
1#
#50400
b1000000000000000 ;
b11 <
bz (
bz 1
bz )
bz 2
bz '
bz 0
#51000
b1111111110000000000000010000000000000000 %
b11010 /
0#
#51600
b1000000000000000 (
b1000000000000000 1
b1000000000000000 )
b1000000000000000 2
b11 '
b11 0
#52000
b10000000000000010000000000000000 !
b10000000000000010000000000000000 8
b11001 $
b1000000000000000000000000000000 4
b11 3
b1111111101000000000000011000000000000000 5
1#
#52400
b111111111111111 ;
b10 <
bz (
bz 1
bz )
bz 2
bz '
bz 0
#53000
b1111111101000000000000011000000000000000 %
b11011 /
0#
#53600
b111111111111111 (
b111111111111111 1
b1000000000000000 )
b1000000000000000 2
b10 '
b10 0
#54000
b1000000000000011000000000000000 !
b1000000000000011000000000000000 8
b1111111111000000000000001000000000000000 4
b10 3
b11010 $
b1111111110000000000000000000000000000000 5
b11 6
1#
#54400
bz (
bz 1
bz )
bz 2
bz '
bz 0
#55000
b1111111110000000000000000000000000000000 %
b11100 /
0#
#55600
b111111111111111 (
b111111111111111 1
b1000000000000000 )
b1000000000000000 2
b10 '
b10 0
#56000
b10000000000000000000000000000000 !
b10000000000000000000000000000000 8
b11011 $
b1111111101000000000000001000000000000000 5
b10 6
1#
#56400
bz (
bz 1
bz )
bz 2
bz '
bz 0
#57000
b1111111101000000000000001000000000000000 %
b11101 /
0#
