mac/mac.v
module mac (instruction, multiplier, multiplicand, stall, clk, reset_n, result, protect);
input signed [15:0] multiplier;
input signed [15:0] multiplicand; 
input  clk;
input  reset_n;
input  stall;
input  [2:0] instruction;
output reg [31:0] result;
output reg [7:0] protect;
reg signed [31:0] reg_result_tmp_1;
reg signed [31:0] reg_result_tmp_2;
reg signed [31:0] reg_result_tmp_3;
reg [7:0] reg_protect;

  always@(posedge clk or negedge reset_n) begin
    if(~reset_n) begin
      reg_result_tmp_1 <= 32'b0;
      reg_result_tmp_2 <= 32'b0;
      reg_result_tmp_3 <= 32'b0;
      result <= 32'b0;
      protect <= 8'b0;
    end else begin
      reg_result_tmp_2 <= reg_result_tmp_1;
      reg_result_tmp_3 <= reg_result_tmp_2;
      result <= reg_result_tmp_3;
    end
  end

  always@(*) begin
    // reg_protect = protect;
    case(instruction)
      3'b000: begin
        // reg_result_tmp = 32'b0;
        // reg_protect = 8'b0;
        reg_result_tmp_1 = multiplier * multiplicand;
      end
      3'b001: begin
         reg_result_tmp_1 = multiplier * multiplicand;
      end
      3'b010: begin
         reg_result_tmp_1 = multiplier * multiplicand;
      end
      3'b011: begin
         reg_result_tmp_1 = multiplier * multiplicand;
      end
      3'b100: begin
        // reg_result_tmp = 32'b0;
        // reg_protect = 8'b0;
        reg_result_tmp_1 = multiplier * multiplicand;
      end
      3'b101: begin
         reg_result_tmp_1 = multiplier * multiplicand;
      end
      3'b110: begin
         reg_result_tmp_1 = multiplier * multiplicand;
      end
      3'b111: begin
         reg_result_tmp_1 = multiplier * multiplicand;
      end
    endcase
  end

endmodule

mac/testfixture.v
// +FHDR------------------------------------------------------------------------
// Copyright (c) 2002, Global UniChip Corporation (UniChip).
// UniChip's Proprietary/Confidential
//
// All rights reserved. No part of this design may be reproduced or stored
// in a retrieval system, or transmitted, in any form or by any means,
// electronic, mechanical, photocopying, recording, or otherwise,
// without prior written permission of the Global UniChip Corporation.
// Unauthorized reproduction, duplication, use, or disclosure of this
// design will be deemed as infringement.
// -----------------------------------------------------------------------------
// FILE   : $Id: dic_2003.v,v 1.1 2003/04/25 04:01:19 ip01_11a Exp $
// TYPE   : Verilog Module
// AUTHOR : Tian-Sheuan Chang 
// -----------------------------------------------------------------------------
// KEYWORDS : 
// -----------------------------------------------------------------------------
// PURPOSE : 
// -----------------------------------------------------------------------------
// PARAMETERS
// PARAM_NAME RANGE : DESCRIPTION : DEFAULT
// N/A
// -----------------------------------------------------------------------------
// REUSE ISSUES
// Reset Strategy :  rst_n
// Clock Domains :   clk
// Critical Timing :
// Test Features :   N/A
// Asynchronous I/F :N/A
// Scan Methodology :MUX-based scan F.F.
// Instantiations :  N/A
// Other :           N/A
// -FHDR------------------------------------------------------------------------

`timescale 1ns/10ps
module mac_sim;
//define for simulator parameters
`define HPHASE 10
//`define FSDB 1
`define CYCLE (`HPHASE * 2)
`define DUMPFILE_NAME "mac.fsdb"
//define for instruction
parameter CLEAR =  3'b000;
parameter CLEAR2 = 3'b100;
parameter MUL_16 = 3'b001;
parameter MAC_16 = 3'b010;
parameter SAT_16 = 3'b011;
parameter MUL_8  = 3'b101;
parameter MAC_8  = 3'b110;
parameter SAT_8  = 3'b111;

parameter NO_STALL = 0;
parameter STALL    = 1;
// -----------------------------------------------------------------------------
// Constant declarations
// -----------------------------------------------------------------------------

// -----------------------------------------------------------------------------
// Signal declarations
// -----------------------------------------------------------------------------

reg             reset_n;
reg             clk;
reg             stall;
reg [2:0]       instruction;
reg [15:0]      multiplier;
reg [15:0]      multiplicand;

// Beginning of automatic wires (for instantiated-module outputs)
wire [7:0]		protect;		// From u_mac of mac.v, ...
wire [31:0]		result;			// From u_mac of mac.v, ...
reg [7:0]		protect_g;		// From u_mac of mac.v, ...
reg [31:0]		result_g;		// From u_mac of mac.v, ...


// End of automatics

// ========================= Start of Main Code ================================
  mac u_mac(/*autoinst*/
	    // Outputs
	    .result			(result[31:0]),
	    .protect			(protect[7:0]),
	    // Inputs
	    .reset_n			(reset_n),
	    .clk			(clk),
	    .multiplier			(multiplier[15:0]),
	    .multiplicand		(multiplicand[15:0]),
	    .instruction		(instruction[2:0]),
	    .stall			(stall));
  
//---- clock generation
always begin
  #(`HPHASE) clk = 1'b0;
  #(`HPHASE) clk = 1'b1;
end

reg [31:0] cycle_cnt;

always @(posedge clk or negedge reset_n)
  if(~reset_n) 
    cycle_cnt <= 0;
  else
    cycle_cnt <= cycle_cnt + 1'b1;

integer result_file1;
integer result_file2;
reg  [39:0] data_base [0:85];
initial $readmemh("EXPECT.DAT", data_base);

integer i;
reg    [39:0] data_tmp;
reg    [9:0]  error_cnt;
reg     ready;

initial begin
      error_cnt = 0;
      @(negedge clk); // start to compare from 2nd cycle
      for  (i = 1; i <= 86; i = i + 1) begin
         data_tmp = data_base[i-1];
         @(negedge clk);
         if (protect !== data_tmp[39:32]) begin
           $display ("ERROR at cycle_cnt= %d: protect(%h)!= EXPECT(%h)", 
                      cycle_cnt, protect, data_tmp[39:32]); 
           error_cnt = error_cnt + 1;
         end
         if (result !== data_tmp[31:0]) begin
           $display ("ERROR at cycle_cnt= %d: result(%h)!= EXPECT(%h)", 
                      cycle_cnt,  result, data_tmp[31:0]); 
           error_cnt = error_cnt + 1;
         end
     end

     if(error_cnt == 10'b0) begin
      $display ("=================================================");
      $display ("Congratulation!, Your design PASSed all the test patterns "); 
      $display ("=================================================");
     end
     else begin
      $display ("=================================================");
      $display ("There're %d errors in your design", error_cnt); 
      $display ("=================================================");
     end
end  

/*
initial 
  $sdf_annotate ("chip.sdf", u_mac);
*/


initial begin
/*  result_file1 = $fopen("mac_rst.txt"); */
/*    result_file2 = $fopen("EXPECT.DAT");    */
  dump_vcd;
  #0 
  clk = 1; 
  reset_n = 1; 
  stall = 1'b0;
  multiplier = 16'bz;
  multiplicand = 16'bz;
  instruction = 3'bz;
  error_cnt = 0;
  ready     = 0;
  $display("start test");
  #(`HPHASE)
     reset_n = 0;
  #(`CYCLE-0.1)  // to prevent from race condition by ccyang
     reset_n = 1;
     test_mac_16;
     test_mac_8;
  #(3* `CYCLE)
     $finish;
end

task test_mac_8;
  begin
  //********************
  mac_tsk(CLEAR, NO_STALL, 16'hff11, 16'h11ff, 0, 0);  

  $display("------------------------------");
  $display("b1. test MUL_8, cycle = %h", cycle_cnt);
  mac_tsk(MUL_8, NO_STALL, 16'h7f7f, 16'h7f7f, protect_g, result_g);  
  mac_tsk(MUL_8, NO_STALL, 16'h8080, 16'h8080, protect_g, result_g);  
  mac_tsk(MUL_8, NO_STALL, 16'h7f7f, 16'h8080, protect_g, result_g);  
  mac_tsk(MUL_8, NO_STALL, 16'h3031, 16'h232f, protect_g, result_g);  
  
  $display("------------------------------");
  $display("b2. test MAC_8, overflow, cycle = %h", cycle_cnt);
  mac_tsk(MAC_8, NO_STALL, 16'h7f7f, 16'h7f7f, protect_g, result_g);  
  mac_tsk(MAC_8, NO_STALL, 16'h7f7f, 16'h7f7f, protect_g, result_g);  
  mac_tsk(MAC_8, NO_STALL, 16'h7f7f, 16'h7f7f, protect_g, result_g);  

  mac_tsk(SAT_8, NO_STALL, 16'h8080, 16'h8080, protect_g, result_g);  

  mac_tsk(MAC_8, NO_STALL, 16'h7f7f, 16'h7f7f, protect_g, result_g);  
  mac_tsk(MAC_8, NO_STALL, 16'h7f7f, 16'h7f7f, protect_g, result_g);  
  mac_tsk(MAC_8, NO_STALL, 16'h7f7f, 16'h7f7f, protect_g, result_g);  
  mac_tsk(MAC_8, NO_STALL, 16'h7f7f, 16'h7f7f, protect_g, result_g);  
  mac_tsk(MAC_8, NO_STALL, 16'h7f7f, 16'h7f7f, protect_g, result_g);  
  mac_tsk(MAC_8, NO_STALL, 16'h7f7f, 16'h7f7f, protect_g, result_g);  
  mac_tsk(MAC_8, NO_STALL, 16'h7f7f, 16'h7f7f, protect_g, result_g);  
  mac_tsk(MAC_8, NO_STALL, 16'h7f7f, 16'h7f7f, protect_g, result_g);  

  $display("------------------------------");
  $display("b3. test stall, cycle = %h", cycle_cnt);
  mac_tsk(SAT_8,    STALL,    16'h8080, 16'h8080, protect_g, result_g);  
  mac_tsk(SAT_8,    NO_STALL, 16'h8080, 16'h8080, protect_g, result_g);  
  
  $display("------------------------------");
  $display("b4. test SAT_8, cycle = %h", cycle_cnt);
  mac_tsk(SAT_8, NO_STALL, 16'h8080, 16'h8080, protect_g, result_g);  
  mac_tsk(CLEAR, NO_STALL, 16'hff11, 16'h11ff, protect_g, result_g);  

  $display("------------------------------");
  $display("b5. test MAC_8, cycle = %h", cycle_cnt);
  mac_tsk(MAC_8, NO_STALL, 16'h807f, 16'h7f7f, protect_g, result_g);  
  mac_tsk(MAC_8, NO_STALL, 16'h807f, 16'h7f7f, protect_g, result_g);  
  mac_tsk(MAC_8, NO_STALL, 16'h807f, 16'h7f7f, protect_g, result_g);  

  mac_tsk(SAT_8, NO_STALL, 16'h807f, 16'h8080, protect_g, result_g);  

  mac_tsk(MAC_8, NO_STALL, 16'h807f, 16'h7f7f, protect_g, result_g);  
  mac_tsk(MAC_8, NO_STALL, 16'h807f, 16'h7f7f, protect_g, result_g);  
  mac_tsk(MAC_8, NO_STALL, 16'h807f, 16'h7f7f, protect_g, result_g);  
  mac_tsk(MAC_8, NO_STALL, 16'h807f, 16'h7f7f, protect_g, result_g);  
  mac_tsk(MAC_8, NO_STALL, 16'h807f, 16'h7f7f, protect_g, result_g);  
  mac_tsk(MAC_8, NO_STALL, 16'h807f, 16'h7f7f, protect_g, result_g);  
  mac_tsk(MAC_8, NO_STALL, 16'h807f, 16'h7f7f, protect_g, result_g);  
  mac_tsk(MAC_8, NO_STALL, 16'h807f, 16'h7f7f, protect_g, result_g);  

  $display("------------------------------");
  $display("b6. stall insertion, cycle = %h", cycle_cnt);
  mac_tsk(SAT_8,    STALL, 16'h8080, 16'h8080, protect_g, result_g);  
  mac_tsk(SAT_8,    STALL, 16'h8080, 16'h8080, protect_g, result_g);  
  mac_tsk(SAT_8, NO_STALL, 16'h8080, 16'h8080, protect_g, result_g);  
  mac_tsk(SAT_8, NO_STALL, 16'h8080, 16'h8080, protect_g, result_g);  
  mac_tsk(MAC_8, NO_STALL, 16'h8080, 16'h7f7f, protect_g, result_g);  
  
  $display("b7. test stall, cycle = %h", cycle_cnt);
  mac_tsk(SAT_8,      STALL, 16'h8080, 16'h8080, protect_g, result_g);  
  mac_tsk(SAT_8,   NO_STALL, 16'h8080, 16'h8080, protect_g, result_g);  

  $display("b8. test SAT_8, cycle = %h", cycle_cnt);
  mac_tsk(SAT_8, NO_STALL, 16'h8080, 16'h8080, protect_g, result_g); 
  mac_tsk(CLEAR, NO_STALL, 16'hff11, 16'h11ff, protect_g, result_g);  

  //********************
  end
endtask

task test_mac_16;
  begin
  //********************
  mac_tsk(CLEAR, NO_STALL, 16'hff11, 16'h11ff, 0, 0);  

  $display("------------------------------");
  $display("a1. test MUL_16, cycle = %h", cycle_cnt);
  mac_tsk(MUL_16, NO_STALL, 16'h7fff, 16'h7fff, protect_g, result_g);  
  mac_tsk(MUL_16, NO_STALL, 16'h8000, 16'h8000, protect_g, result_g);  
  mac_tsk(MUL_16, NO_STALL, 16'h7fff, 16'h8000, protect_g, result_g);  
  mac_tsk(MUL_16, NO_STALL, 16'h3031, 16'h232f, protect_g, result_g);  
  
  $display("------------------------------");
  $display("a2. test MAC_16, overflow, cycle = %h", cycle_cnt);
  mac_tsk(MAC_16, NO_STALL, 16'h7fff, 16'h7fff, protect_g, result_g);  
  mac_tsk(MAC_16, NO_STALL, 16'h7fff, 16'h7fff, protect_g, result_g);  
  mac_tsk(MAC_16, NO_STALL, 16'h7fff, 16'h7fff, protect_g, result_g);  

  mac_tsk(SAT_16, NO_STALL, 16'h8000, 16'h8000, protect_g, result_g);  

  mac_tsk(MAC_16, NO_STALL, 16'h7fff, 16'h7fff, protect_g, result_g);  
  mac_tsk(MAC_16, NO_STALL, 16'h7fff, 16'h7fff, protect_g, result_g);  
  mac_tsk(MAC_16, NO_STALL, 16'h7fff, 16'h7fff, protect_g, result_g);  
  mac_tsk(MAC_16, NO_STALL, 16'h7fff, 16'h7fff, protect_g, result_g);  
  mac_tsk(MAC_16, NO_STALL, 16'h7fff, 16'h7fff, protect_g, result_g);  
  mac_tsk(MAC_16, NO_STALL, 16'h7fff, 16'h7fff, protect_g, result_g);  
  mac_tsk(MAC_16, NO_STALL, 16'h7fff, 16'h7fff, protect_g, result_g);  
  mac_tsk(MAC_16, NO_STALL, 16'h7fff, 16'h7fff, protect_g, result_g);  

  $display("------------------------------");
  $display("a3. test stall, cycle = %h", cycle_cnt);
  mac_tsk(SAT_16,    STALL, 16'h8000, 16'h8000, protect_g, result_g);  
  mac_tsk(SAT_16, NO_STALL, 16'h8000, 16'h8000, protect_g, result_g);  
  
  $display("------------------------------");
  $display("a4. test SAT_16, cycle = %h", cycle_cnt);
  mac_tsk(SAT_16, NO_STALL, 16'h8000, 16'h8000, protect_g, result_g);  
  mac_tsk(CLEAR,  NO_STALL, 16'hff11, 16'h11ff, protect_g, result_g);  

  $display("------------------------------");
  $display("a5. test MAC_16, cycle = %h", cycle_cnt);
  mac_tsk(MAC_16, NO_STALL, 16'h8000, 16'h7fff, protect_g, result_g);  
  mac_tsk(MAC_16, NO_STALL, 16'h8000, 16'h7fff, protect_g, result_g);  
  mac_tsk(MAC_16, NO_STALL, 16'h8000, 16'h7fff, protect_g, result_g);  

  mac_tsk(SAT_16, NO_STALL, 16'h8000, 16'h8000, protect_g, result_g);  

  mac_tsk(MAC_16, NO_STALL, 16'h8000, 16'h7fff, protect_g, result_g);  
  mac_tsk(MAC_16, NO_STALL, 16'h8000, 16'h7fff, protect_g, result_g);  
  mac_tsk(MAC_16, NO_STALL, 16'h8000, 16'h7fff, protect_g, result_g);  
  mac_tsk(MAC_16, NO_STALL, 16'h8000, 16'h7fff, protect_g, result_g);  
  mac_tsk(MAC_16, NO_STALL, 16'h8000, 16'h7fff, protect_g, result_g);  
  mac_tsk(MAC_16, NO_STALL, 16'h8000, 16'h7fff, protect_g, result_g);  
  mac_tsk(MAC_16, NO_STALL, 16'h8000, 16'h7fff, protect_g, result_g);  
  mac_tsk(MAC_16, NO_STALL, 16'h8000, 16'h7fff, protect_g, result_g);  

  $display("------------------------------");
  $display("a6. stall insertion, cycle = %h", cycle_cnt);
  mac_tsk(SAT_16,    STALL, 16'h8000, 16'h8000, protect_g, result_g);  
  mac_tsk(SAT_16,    STALL, 16'h8000, 16'h8000, protect_g, result_g);  
  mac_tsk(SAT_16, NO_STALL, 16'h8000, 16'h8000, protect_g, result_g);  
  mac_tsk(SAT_16,    STALL, 16'h8000, 16'h8000, protect_g, result_g);  
  mac_tsk(MAC_16, NO_STALL, 16'h8000, 16'h7fff, protect_g, result_g);  
  
  $display("a7. test stall, cycle = %h", cycle_cnt);
  mac_tsk(SAT_16,    STALL, 16'h8000, 16'h8000, protect_g, result_g);  

  $display("a8. test SAT_16, cycle = %h", cycle_cnt);
  mac_tsk(SAT_16, NO_STALL, 16'h8000, 16'h8000, protect_g, result_g); 
  mac_tsk(CLEAR,  NO_STALL, 16'hff11, 16'h11ff, protect_g, result_g);  

  //********************
  
  end
endtask

task mac_tsk;
  input [2:0] instruction_t;
  input stall_t;
  input [15:0] a;
  input [15:0] b;
  
  input [7:0] protect_t; //unused, for on-line verification
  input [31:0] result_t; //unused, for on-line verification
  
  begin
    @(negedge clk)
    #(`CYCLE*0.3)
      instruction = instruction_t;
      multiplier = a;
      multiplicand = b;
      stall = stall_t; 
      protect_g = protect_t;
      result_g = result_t;
    #(`CYCLE*0.4)
      instruction = 3'bz;
      multiplier = 16'bz;
      multiplicand = 16'bz;
      stall = 1'b0;
      protect_g = protect_t;
      result_g = result_t;  
  end
endtask  

//*********************
//compare result
//*********************
always @(negedge clk) begin
//  $fdisplay(result_file1,"cycles = %h,  %h,  %h", cycle_cnt, protect, result);
//    $fdisplay(result_file2,"%h%h", protect, result);
  end

//*********************
// Dump waveform
//*********************

task dump_vcd;
begin
$dumpfile("mac.vcd");
$dumpvars;    
`ifdef FSDB
  //$fsdbVersion;
  $fsdbDumpfile(`DUMPFILE_NAME);
  $fsdbDumpvars;
`endif
 end
endtask

endmodule // module_name

// ============================ End of Module ==================================
// Revision History
// $Log: dic_2003.v,v $
// Revision 1.1  2003/04/25 04:01:19  ip01_11a
// for ic test
//
// Revision 1.1.1.1  2003/04/15 03:30:42  ip01_11a
// first version
//

mac/mac.vcd
$date
	Mon Apr 11 23:39:22 2022
$end
$version
	Icarus Verilog
$end
$timescale
	10ps
$end
$scope module mac_sim $end
$var wire 32 ! result [31:0] $end
$var wire 8 " protect [7:0] $end
$var reg 1 # clk $end
$var reg 32 $ cycle_cnt [31:0] $end
$var reg 40 % data_tmp [39:0] $end
$var reg 10 & error_cnt [9:0] $end
$var reg 3 ' instruction [2:0] $end
$var reg 16 ( multiplicand [15:0] $end
$var reg 16 ) multiplier [15:0] $end
$var reg 8 * protect_g [7:0] $end
$var reg 1 + ready $end
$var reg 1 , reset_n $end
$var reg 32 - result_g [31:0] $end
$var reg 1 . stall $end
$var integer 32 / i [31:0] $end
$scope module u_mac $end
$var wire 1 # clk $end
$var wire 3 0 instruction [2:0] $end
$var wire 16 1 multiplicand [15:0] $end
$var wire 16 2 multiplier [15:0] $end
$var wire 1 , reset_n $end
$var wire 1 . stall $end
$var reg 8 3 protect [7:0] $end
$var reg 32 4 reg_result_tmp_1 [31:0] $end
$var reg 32 5 reg_result_tmp_2 [31:0] $end
$var reg 32 6 reg_result_tmp_3 [31:0] $end
$var reg 32 7 result [31:0] $end
$upscope $end
$scope task dump_vcd $end
$upscope $end
$scope task mac_tsk $end
$var reg 16 8 a [15:0] $end
$var reg 16 9 b [15:0] $end
$var reg 3 : instruction_t [2:0] $end
$var reg 8 ; protect_t [7:0] $end
$var reg 32 < result_t [31:0] $end
$var reg 1 = stall_t $end
$upscope $end
$scope task test_mac_16 $end
$upscope $end
$scope task test_mac_8 $end
$upscope $end
$upscope $end
$enddefinitions $end
#0
$dumpvars
x=
bx <
bx ;
bx :
bx 9
bx 8
bx 7
bx 6
bx 5
bx 4
bx 3
bz 2
bz 1
bz 0
bx /
0.
bx -
1,
0+
bx *
bz )
bz (
bz '
b0 &
bx %
bx $
1#
bx "
bx !
$end
#1000
b0 $
b0 "
b0 3
b0 !
b0 7
b0 6
b0 5
b0 4
b0 %
b1 /
0,
0#
#2000
1#
#2990
b0 <
b0 ;
b1000111111111 9
b1111111100010001 8
0=
b0 :
1,
#3000
b10 /
0#
#3600
b11111111111011110011001011101111 4
b0 -
b0 *
b1000111111111 (
b1000111111111 1
b1111111100010001 )
b1111111100010001 2
b0 '
b0 0
#4000
b1 $
b11111111111011110011001011101111 5
1#
#4400
b111111111111111 9
b111111111111111 8
b1 :
bz (
bz 1
bz )
bz 2
bz '
bz 0
#5000
b11 /
0#
#5600
b111111111111110000000000000001 4
b111111111111111 (
b111111111111111 1
b111111111111111 )
b111111111111111 2
b1 '
b1 0
#6000
b11111111111011110011001011101111 6
b111111111111110000000000000001 5
b10 $
1#
#6400
b1000000000000000 9
b1000000000000000 8
bz (
bz 1
bz )
bz 2
bz '
bz 0
#7000
b100 /
0#
#7600
b1000000000000000000000000000000 4
b1000000000000000 (
b1000000000000000 1
b1000000000000000 )
b1000000000000000 2
b1 '
b1 0
#8000
b11 $
b11111111111011110011001011101111 !
b11111111111011110011001011101111 7
b111111111111110000000000000001 6
b1000000000000000000000000000000 5
1#
#8400
b111111111111111 8
bz (
bz 1
bz )
bz 2
bz '
bz 0
#9000
b111111111111110000000000000001 %
b101 /
b1 &
0#
#9600
b11000000000000001000000000000000 4
b1000000000000000 (
b1000000000000000 1
b111111111111111 )
b111111111111111 2
b1 '
b1 0
#10000
b111111111111110000000000000001 !
b111111111111110000000000000001 7
b1000000000000000000000000000000 6
b11000000000000001000000000000000 5
b100 $
1#
#10400
b10001100101111 9
b11000000110001 8
bz (
bz 1
bz )
bz 2
bz '
bz 0
#11000
b1000000000000000000000000000000 %
b110 /
0#
#11600
b110100111111000101111111111 4
b10001100101111 (
b10001100101111 1
b11000000110001 )
b11000000110001 2
b1 '
b1 0
#12000
b101 $
b1000000000000000000000000000000 !
b1000000000000000000000000000000 7
b11000000000000001000000000000000 6
b110100111111000101111111111 5
1#
#12400
b111111111111111 9
b111111111111111 8
b10 :
bz (
bz 1
bz )
bz 2
bz '
bz 0
#13000
b1111111111000000000000001000000000000000 %
b111 /
0#
#13600
b111111111111110000000000000001 4
b111111111111111 (
b111111111111111 1
b111111111111111 )
b111111111111111 2
b10 '
b10 0
#14000
b11000000000000001000000000000000 !
b11000000000000001000000000000000 7
b110100111111000101111111111 6
b111111111111110000000000000001 5
b110 $
1#
#14400
bz (
bz 1
bz )
bz 2
bz '
bz 0
#15000
b110100111111000101111111111 %
b1000 /
b10 &
0#
#15600
b111111111111111 (
b111111111111111 1
b111111111111111 )
b111111111111111 2
b10 '
b10 0
#16000
b111 $
b110100111111000101111111111 !
b110100111111000101111111111 7
b111111111111110000000000000001 6
1#
#16400
bz (
bz 1
bz )
bz 2
bz '
bz 0
#17000
b1000110100111101000110000000000 %
b1001 /
0#
#17600
b111111111111111 (
b111111111111111 1
b111111111111111 )
b111111111111111 2
b10 '
b10 0
#18000
b111111111111110000000000000001 !
b111111111111110000000000000001 7
b1000 $
1#
#18400
b1000000000000000 9
b1000000000000000 8
b11 :
bz (
bz 1
bz )
bz 2
bz '
bz 0
#19000
b10000110100111011000110000000001 %
b1010 /
b11 &
0#
#19600
b1000000000000000000000000000000 4
b1000000000000000 (
b1000000000000000 1
b1000000000000000 )
b1000000000000000 2
b11 '
b11 0
#20000
b1001 $
b1000000000000000000000000000000 5
1#
#20400
b111111111111111 9
b111111111111111 8
b10 :
bz (
bz 1
bz )
bz 2
bz '
bz 0
#21000
b11000110100111001000110000000010 %
b1011 /
b100 &
0#
#21600
b111111111111110000000000000001 4
b111111111111111 (
b111111111111111 1
b111111111111111 )
b111111111111111 2
b10 '
b10 0
#22000
b1000000000000000000000000000000 6
b111111111111110000000000000001 5
b1010 $
1#
#22400
bz (
bz 1
bz )
bz 2
bz '
bz 0
#23000
b1111111111111111111111111111111 %
b1100 /
b101 &
0#
#23600
b111111111111111 (
b111111111111111 1
b111111111111111 )
b111111111111111 2
b10 '
b10 0
#24000
b1011 $
b1000000000000000000000000000000 !
b1000000000000000000000000000000 7
b111111111111110000000000000001 6
1#
#24400
bz (
bz 1
bz )
bz 2
bz '
bz 0
#25000
b10111111111111110000000000000000 %
b1101 /
b110 &
0#
#25600
b111111111111111 (
b111111111111111 1
b111111111111111 )
b111111111111111 2
b10 '
b10 0
#26000
b111111111111110000000000000001 !
b111111111111110000000000000001 7
b1100 $
1#
#26400
bz (
bz 1
bz )
bz 2
bz '
bz 0
#27000
b11111111111111100000000000000001 %
b1110 /
b111 &
0#
#27600
b111111111111111 (
b111111111111111 1
b111111111111111 )
b111111111111111 2
b10 '
b10 0
#28000
b1101 $
1#
#28400
bz (
bz 1
bz )
bz 2
bz '
bz 0
#29000
b100111111111111010000000000000010 %
b1111 /
b1000 &
0#
#29600
b111111111111111 (
b111111111111111 1
b111111111111111 )
b111111111111111 2
b10 '
b10 0
#30000
b1110 $
1#
#30400
bz (
bz 1
bz )
bz 2
bz '
bz 0
#31000
b101111111111111000000000000000011 %
b10000 /
b1010 &
0#
#31600
b111111111111111 (
b111111111111111 1
b111111111111111 )
b111111111111111 2
b10 '
b10 0
#32000
b1111 $
1#
#32400
bz (
bz 1
bz )
bz 2
bz '
bz 0
#33000
b110111111111110110000000000000100 %
b10001 /
b1100 &
0#
#33600
b111111111111111 (
b111111111111111 1
b111111111111111 )
b111111111111111 2
b10 '
b10 0
#34000
b10000 $
1#
#34400
bz (
bz 1
bz )
bz 2
bz '
bz 0
#35000
b111111111111110100000000000000101 %
b10010 /
b1110 &
0#
#35600
b111111111111111 (
b111111111111111 1
b111111111111111 )
b111111111111111 2
b10 '
b10 0
#36000
b10001 $
1#
#36400
b1000000000000000 9
b1000000000000000 8
1=
b11 :
bz (
bz 1
bz )
bz 2
bz '
bz 0
#37000
b10011 /
b10000 &
0#
#37600
b1000000000000000000000000000000 4
1.
b1000000000000000 (
b1000000000000000 1
b1000000000000000 )
b1000000000000000 2
b11 '
b11 0
#38000
b1000000000000000000000000000000 5
b10010 $
1#
#38400
0=
0.
bz (
bz 1
bz )
bz 2
bz '
bz 0
#39000
b1000111111111110010000000000000110 %
b10100 /
b10010 &
0#
#39600
b1000000000000000 (
b1000000000000000 1
b1000000000000000 )
b1000000000000000 2
b11 '
b11 0
#40000
b10011 $
b1000000000000000000000000000000 6
1#
#40400
bz (
bz 1
bz )
bz 2
bz '
bz 0
#41000
b1001111111111110000000000000000111 %
b10101 /
b10100 &
0#
#41600
b1000000000000000 (
b1000000000000000 1
b1000000000000000 )
b1000000000000000 2
b11 '
b11 0
#42000
b1000000000000000000000000000000 !
b1000000000000000000000000000000 7
b10100 $
1#
#42400
b1000111111111 9
b1111111100010001 8
b0 :
bz (
bz 1
bz )
bz 2
bz '
bz 0
#43000
b1001111111111111111111111111111111 %
b10110 /
b10110 &
0#
#43600
b11111111111011110011001011101111 4
b1000111111111 (
b1000111111111 1
b1111111100010001 )
b1111111100010001 2
b0 '
b0 0
#44000
b10101 $
b11111111111011110011001011101111 5
1#
#44400
b111111111111111 9
b1000000000000000 8
b10 :
bz (
bz 1
bz )
bz 2
bz '
bz 0
#45000
b10111 /
b11000 &
0#
#45600
b11000000000000001000000000000000 4
b111111111111111 (
b111111111111111 1
b1000000000000000 )
b1000000000000000 2
b10 '
b10 0
#46000
b11111111111011110011001011101111 6
b11000000000000001000000000000000 5
b10110 $
1#
#46400
bz (
bz 1
bz )
bz 2
bz '
bz 0
#47000
b0 %
b11000 /
b11010 &
0#
#47600
b111111111111111 (
b111111111111111 1
b1000000000000000 )
b1000000000000000 2
b10 '
b10 0
#48000
b10111 $
b11111111111011110011001011101111 !
b11111111111011110011001011101111 7
b11000000000000001000000000000000 6
1#
#48400
bz (
bz 1
bz )
bz 2
bz '
bz 0
#49000
b1111111111000000000000001000000000000000 %
b11001 /
b11011 &
0#
#49600
b111111111111111 (
b111111111111111 1
b1000000000000000 )
b1000000000000000 2
b10 '
b10 0
#50000
b11000000000000001000000000000000 !
b11000000000000001000000000000000 7
b11000 $
1#
#50400
b1000000000000000 9
b11 :
bz (
bz 1
bz )
bz 2
bz '
bz 0
#51000
b1111111110000000000000010000000000000000 %
b11010 /
b11100 &
0#
#51600
b1000000000000000000000000000000 4
b1000000000000000 (
b1000000000000000 1
b1000000000000000 )
b1000000000000000 2
b11 '
b11 0
#52000
b11001 $
b1000000000000000000000000000000 5
1#
#52400
b111111111111111 9
b10 :
bz (
bz 1
bz )
bz 2
bz '
bz 0
#53000
b1111111101000000000000011000000000000000 %
b11011 /
b11110 &
0#
#53600
b11000000000000001000000000000000 4
b111111111111111 (
b111111111111111 1
b1000000000000000 )
b1000000000000000 2
b10 '
b10 0
#54000
b1000000000000000000000000000000 6
b11000000000000001000000000000000 5
b11010 $
1#
#54400
bz (
bz 1
bz )
bz 2
bz '
bz 0
#55000
b1111111110000000000000000000000000000000 %
b11100 /
b100000 &
0#
#55600
b111111111111111 (
b111111111111111 1
b1000000000000000 )
b1000000000000000 2
b10 '
b10 0
#56000
b11011 $
b1000000000000000000000000000000 !
b1000000000000000000000000000000 7
b11000000000000001000000000000000 6
1#
#56400
bz (
bz 1
bz )
bz 2
bz '
bz 0
#57000
b1111111101000000000000001000000000000000 %
b11101 /
b100010 &
0#
#57600
b111111111111111 (
b111111111111111 1
b1000000000000000 )
b1000000000000000 2
b10 '
b10 0
#58000
b11000000000000001000000000000000 !
b11000000000000001000000000000000 7
b11100 $
1#
#58400
bz (
bz 1
bz )
bz 2
bz '
bz 0
#59000
b1111111100000000000000010000000000000000 %
b11110 /
b100100 &
0#
#59600
b111111111111111 (
b111111111111111 1
b1000000000000000 )
b1000000000000000 2
b10 '
b10 0
#60000
b11101 $
1#
#60400
bz (
bz 1
bz )
bz 2
bz '
bz 0
#61000
b1111111011000000000000011000000000000000 %
b11111 /
b100110 &
0#
#61600
b111111111111111 (
b111111111111111 1
b1000000000000000 )
b1000000000000000 2
b10 '
b10 0
#62000
b11110 $
1#
#62400
bz (
bz 1
bz )
bz 2
bz '
bz 0
#63000
b1111111010000000000000100000000000000000 %
b100000 /
b101000 &
0#
#63600
b111111111111111 (
b111111111111111 1
b1000000000000000 )
b1000000000000000 2
b10 '
b10 0
#64000
b11111 $
1#
#64400
bz (
bz 1
bz )
bz 2
bz '
bz 0
#65000
b1111111001000000000000101000000000000000 %
b100001 /
b101010 &
0#
#65600
b111111111111111 (
b111111111111111 1
b1000000000000000 )
b1000000000000000 2
b10 '
b10 0
#66000
b100000 $
1#
#66400
bz (
bz 1
bz )
bz 2
bz '
bz 0
#67000
b1111111000000000000000110000000000000000 %
b100010 /
b101100 &
0#
#67600
b111111111111111 (
b111111111111111 1
b1000000000000000 )
b1000000000000000 2
b10 '
b10 0
#68000
b100001 $
1#
#68400
b1000000000000000 9
1=
b11 :
bz (
bz 1
bz )
bz 2
bz '
bz 0
#69000
b100011 /
b101110 &
0#
#69600
b1000000000000000000000000000000 4
1.
b1000000000000000 (
b1000000000000000 1
b1000000000000000 )
b1000000000000000 2
b11 '
b11 0
#70000
b1000000000000000000000000000000 5
b100010 $
1#
#70400
0.
bz (
bz 1
bz )
bz 2
bz '
bz 0
#71000
b100100 /
b110000 &
0#
#71600
1.
b1000000000000000 (
b1000000000000000 1
b1000000000000000 )
b1000000000000000 2
b11 '
b11 0
